CHANGES.txt
README.txt
bootstrap.py
buildout.cfg
setup.py
src/hurry/__init__.py
src/hurry.jquerylayout.egg-info/PKG-INFO
src/hurry.jquerylayout.egg-info/SOURCES.txt
src/hurry.jquerylayout.egg-info/dependency_links.txt
src/hurry.jquerylayout.egg-info/entry_points.txt
src/hurry.jquerylayout.egg-info/namespace_packages.txt
src/hurry.jquerylayout.egg-info/not-zip-safe
src/hurry.jquerylayout.egg-info/requires.txt
src/hurry.jquerylayout.egg-info/top_level.txt
src/hurry/jquerylayout/__init__.py
src/hurry/jquerylayout/jquerylayout.txt
src/hurry/jquerylayout/tests.py
src/hurry/jquerylayout/jquerylayout-build/jquery.layout.js
src/hurry/jquerylayout/jquerylayout-build/jquery.layout.min.js
src/hurry/jquerylayout/jquerylayout-build/layout.css