Metadata-Version: 1.0
Name: hurry.jquerylayout
Version: 1.2.0.2
Summary: hurry.resource style resources for jQuery UI.Layout.
Home-page: UNKNOWN
Author: Martijn Faassen
Author-email: faassen@startifact.com
License: MIT
Keywords: hurry.resource jquery
Platform: UNKNOWN
